{
  "neoforge:conditions": [
    {
      "type": "neoforge:and",
      "values": [
        {
          "type": "neoforge:not",
          "value": {
            "type": "neoforge:mod_loaded",
            "modid": "mekanism"
          }
        },
        {
          "type": "neoforge:false"
        }
      ]
    }
  ],
  "type": "minecraft:crafting_shapeless",
  "category": "misc",
  "ingredients": [
    {
      "item": "mekanism:qio_drive_hyper_dense"
    },
    {
      "item": "mekanism:qio_drive_hyper_dense"
    },
    {
      "item": "mekanism:qio_drive_hyper_dense"
    },
    {
      "item": "mekanism:qio_drive_hyper_dense"
    },
    {
      "tag": "forge:seeds"
    }
  ],
  "result": {
    "item": "growablecells:seed_mek_qio_hyper_drive"
  }
}